otter_cli/__init__.py
otter_cli-0.0.1.data/scripts/otter
otter_cli-0.0.1.dist-info/DESCRIPTION.rst
otter_cli-0.0.1.dist-info/METADATA
otter_cli-0.0.1.dist-info/RECORD
otter_cli-0.0.1.dist-info/WHEEL
otter_cli-0.0.1.dist-info/metadata.json
otter_cli-0.0.1.dist-info/top_level.txt
