Metadata-Version: 2.0
Name: otter-cli
Version: 0.0.1
Summary: Command line interface for interacting with Otter Web API
Home-page: UNKNOWN
Author: UNKNOWN
Author-email: UNKNOWN
License: UNKNOWN
Platform: UNKNOWN
